celery_explorer/__init__.py
celery_explorer/admin.py
celery_explorer/apps.py
celery_explorer/forms.py
celery_explorer/models.py
celery_explorer/tests.py
celery_explorer/urls.py
celery_explorer/views.py
celery_explorer/migrations/__init__.py
celery_explorer/static/explorer_static/css/styles.css
celery_explorer/static/explorer_static/js/scripts.js
celery_explorer/templates/task_list.html
celery_explorer-0.2.2.dist-info/LICENSE
celery_explorer-0.2.2.dist-info/METADATA
celery_explorer-0.2.2.dist-info/WHEEL
celery_explorer-0.2.2.dist-info/top_level.txt
celery_explorer-0.2.2.dist-info/RECORD
